{"name":"Wilhelm-Bölsche-Schule (Integrierte Sekundarschule)","id":"BE-16209","address":"Aßmannstr. 11, 12587 Berlin","website":"http://www.wbs.schule-berlin.net","email":"sekretariat.bos@t-online.de","school_type":"Integrierte Sekundarschule","legal_status":1,"fax":"6458914","phone":"6455089","director":"Hr. Dr. Schulze","full_time_school":true,"profile":{"teacher":[{"year":"2010/11","female":19,"male":6},{"year":"2011/12","female":22,"male":9},{"year":"2012/13","female":20,"male":13},{"year":"2013/14","female":24,"male":12},{"year":"2014/15","female":29,"male":14},{"year":"2015/16","female":30,"male":15}],"students":{"2010/11":[{"class_level":"Jahrgangsstufe 07","female":33,"male":41},{"class_level":"Jahrgangsstufe 08","female":36,"male":50},{"class_level":"Jahrgangsstufe 09","female":29,"male":54},{"class_level":"Jahrgangsstufe 10","female":25,"male":54}],"2011/12":[{"class_level":"Jahrgangsstufe 07","female":37,"male":79},{"class_level":"Jahrgangsstufe 08","female":37,"male":41},{"class_level":"Jahrgangsstufe 09","female":37,"male":50},{"class_level":"Jahrgangsstufe 10","female":29,"male":53}],"2012/13":[{"class_level":"Jahrgangsstufe 07","female":53,"male":47},{"class_level":"Jahrgangsstufe 08","female":35,"male":81},{"class_level":"Jahrgangsstufe 09","female":38,"male":44},{"class_level":"Jahrgangsstufe 10","female":34,"male":55}],"2013/14":[{"class_level":"Jahrgangsstufe 07","female":38,"male":50},{"class_level":"Jahrgangsstufe 08","female":52,"male":50},{"class_level":"Jahrgangsstufe 09","female":44,"male":82},{"class_level":"Jahrgangsstufe 10","female":38,"male":47}],"2014/15":[{"class_level":"Jahrgangsstufe 07","female":37,"male":57},{"class_level":"Jahrgangsstufe 08","female":38,"male":52},{"class_level":"Jahrgangsstufe 09","female":53,"male":47},{"class_level":"Jahrgangsstufe 10","female":39,"male":81}],"2015/16":[{"class_level":"Jahrgangsstufe 07","female":45,"male":49},{"class_level":"Jahrgangsstufe 08","female":45,"male":57},{"class_level":"Jahrgangsstufe 09","female":40,"male":59},{"class_level":"Jahrgangsstufe 10","female":52,"male":55}],"2016/17":[{"class_level":"Jahrgangsstufe 07","female":42,"male":58},{"class_level":"Jahrgangsstufe 08","female":48,"male":57},{"class_level":"Jahrgangsstufe 09","female":46,"male":59},{"class_level":"Jahrgangsstufe 10","female":50,"male":71}]}},"programs":{"working_groups":[{"name":"WAT","category":"no category","entity":"no group"},{"name":"Bildende Kunst","category":"Kunst / Kultur","entity":"Bildende Kunst"},{"name":"Sport","category":"Sport","entity":"Sport"},{"name":"Medien- und Hardwaretechnik","category":"no category","entity":"no group"},{"name":"Kochen","category":"Handwerk","entity":"Kochen"},{"name":"Darstellendes Spiel","category":"Gesellschaft / Partizipation","entity":"Darstellendes Spiel"},{"name":"Fördern und Fordern","category":"no category","entity":"no group"},{"name":"Hausaufgabenbetreuung","category":"Berufsorientierung","entity":"Hausaufgabenbetreuung"}],"programs":["Schule ohne Rassismus - Schule mit Courage"]},"concept":"Leitbild der Wilhelm-Bölsche-SchuleSchulisches Leben heißt für uns:Befähigen zu eigenverantwortlichem Lernen und menschlichem MiteinanderUnser Verständnis von Unterricht schließt Praxis- und Zukunftsorientierung der Lehre gleichermaßen einAnstrengen lohnt sich!Schulisches Leben mit all seiner Vielfalt bedeutet uns:handlungsorientierten Lernmethoden und individuellem VerstehenLernen durch BegreifenSchulisches Leben äußert sich für uns:Im Verständnis füreinander.Respektieren und Einhalten von Grenzen - als Zeichen gegenseitiger AchtungWir leben Zusammenhalt!Schulisches Leben bedeutet für uns: das Wirken in der Gemeinschaft, das den Mut und die Zuversicht aufbaut, selbstbewusst Wege in die Zukunft zu finden und zu gehenNur wer an sich glaubt, hat Zukunft!Nicht nur als Randnotiz: Die Wilhelm-Bölsche-Schule sieht sich durchaus in der humanistisch-naturwissenschaftlichen Tradition ihres Namensgebers Das umfasst den Spannungsbogen von unterrichtlichen Inhalten bis zur Wahrnehmung außerschulischer AktivitätenLeitbild","partner":[{"name":"Bölscheclub - Jugendzentrum Friedrichshagen","type":{"detail":null,"mittel":"Familien-/Bildungs-/Kulturzentrum","grob":"Öffentliche Infrastruktur"}},{"name":"METEUM -Technische Kinder- und Jugendakademie des Technischen Jugendbildungsvereins in Praxis e. V. in Zusammenarbeit mit dem Bezirksamt Treptow-Köpenick und dem Freizeit- und Erholungszentrum Wuhlheide (FEZ)","type":{"detail":"Verein","mittel":"Gemeinnütziger Akteur","grob":"Gemeinnütziger Akteur"}}],"state":"BE","lon":13.619242,"lat":52.450949}
