{"name":"OSZ Handel 1","id":"BE-16262","address":"Wrangelstr. 98, 10997 Berlin","website":"http://www.oszhandel.de","email":"leitung@oszhandel1.de","school_type":"Berufliches Gymnasium","legal_status":1,"fax":"611296-15","phone":"611296-0","director":"Hr. Scharke","full_time_school":false,"profile":{"teacher":[{"year":"2003/04","female":117,"male":142},{"year":"2004/05","female":129,"male":146},{"year":"2005/06","female":147,"male":147},{"year":"2006/07","female":156,"male":144},{"year":"2007/08","female":164,"male":139},{"year":"2008/09","female":158,"male":129},{"year":"2009/10","female":156,"male":117},{"year":"2010/11","female":144,"male":108},{"year":"2011/12","female":155,"male":107},{"year":"2012/13","female":153,"male":98},{"year":"2013/14","female":150,"male":81},{"year":"2014/15","female":147,"male":79},{"year":"2015/16","female":147,"male":73}],"students":{}},"programs":{"working_groups":[],"programs":["Schule ohne Rassismus - Schule mit Courage","Schule ohne Rassismus - Schule mit Courage","Schule ohne Rassismus - Schule mit Courage"]},"concept":"Leitbild des Oberstufenzentrum HandelBitte lesen Sie dafür das aktuelle Schulprogramm unter dem untenstehenden linkSchulprogramm","partner":[{"name":"Ausbildungszentrum ROC Nijmegen","type":{"detail":null,"mittel":"Familien-/Bildungs-/Kulturzentrum","grob":"Öffentliche Infrastruktur"}},{"name":"Börsenverein des Deutschen Buchhandels e.V.","type":{"detail":"Verein","mittel":"Gemeinnütziger Akteur","grob":"Gemeinnütziger Akteur"}},{"name":"BWK BildungsWerk in Kreuzberg GmbH","type":{"detail":null,"mittel":"Wirtschaftsakteur","grob":"Wirtschaftsakteur"}},{"name":"Commerzbank AG","type":{"detail":null,"mittel":"Wirtschaftsakteur","grob":"Wirtschaftsakteur"}},{"name":"Daimler AG","type":{"detail":null,"mittel":"Wirtschaftsakteur","grob":"Wirtschaftsakteur"}},{"name":"DekaBank Deutsche Girozentrale","type":{"detail":null,"mittel":"Wirtschaftsakteur","grob":"Wirtschaftsakteur"}},{"name":"Deutsche Rentenversicherung Bund","type":{"detail":null,"mittel":"Öffentliche Infrastruktur (Gesundheitswesen/Altersvorsorge)","grob":"Öffentliche Infrastruktur"}},{"name":"Fachhochschule Brandenburg in Brandenburg an der Havel","type":{"detail":"Universität/Hochschule/Forschungsinstitut","mittel":"Öffentliche Infrastruktur (Bildung/Uni/Hochschule/Forschung)","grob":"Öffentliche Infrastruktur"}},{"name":"Goethe-Institut","type":{"detail":"Verein","mittel":"Gemeinnütziger Akteur","grob":"Gemeinnütziger Akteur"}},{"name":"Handelsverband Deutschland - HDE e.V.","type":{"detail":"Verein","mittel":"Gemeinnütziger Akteur","grob":"Gemeinnütziger Akteur"}},{"name":"Hauptverband des Einzelhandels","type":{"detail":null,"mittel":"Verband / Kammer / Innung","grob":"Verband / Kammer / Innung / Gewerkschaft"}},{"name":"Industrie- und Handelskammer (IHK) zu Berlin","type":{"detail":null,"mittel":"Öffentliche Infrastruktur (Amt)","grob":"Verband / Kammer / Innung / Gewerkschaft"}},{"name":"Institut für Wirtschaftsinformatik der Humboldt-Universität zu Berlin","type":{"detail":"Universität/Hochschule/Forschungsinstitut","mittel":"Öffentliche Infrastruktur (Bildung/Uni/Hochschule/Forschung)","grob":"Öffentliche Infrastruktur"}},{"name":"itw Institut für Aus- und Weiterbildung gGmbH","type":{"detail":"gGmbH","mittel":"Gemeinnütziger Akteur","grob":"Gemeinnütziger Akteur"}},{"name":"SAP Deutschland AG & Co. KG","type":{"detail":null,"mittel":"Wirtschaftsakteur","grob":"Wirtschaftsakteur"}},{"name":"SPI Consult GmbH","type":{"detail":null,"mittel":"Wirtschaftsakteur","grob":"Wirtschaftsakteur"}},{"name":"Werk in Stuttgart-Untertürkheim","type":{"detail":null,"mittel":"Wirtschaftsakteur","grob":"Wirtschaftsakteur"}}],"state":"BE","lon":13.436592,"lat":52.500962}
