{"name":"Nehring-Grundschule","id":"BE-16340","address":"Nehringstr. 9-10, 14059 Berlin","website":"http://www.nehring-grundschule.de","email":"info@nehring-grundschule.de","school_type":"Grundschule","legal_status":1,"fax":"902924-343","phone":"902924-300","director":"Fr. Llappalainen","full_time_school":true,"profile":{"teacher":[{"year":"2003/04","female":33,"male":9},{"year":"2004/05","female":34,"male":9},{"year":"2005/06","female":31,"male":11},{"year":"2006/07","female":36,"male":11},{"year":"2007/08","female":35,"male":10},{"year":"2008/09","female":24,"male":7},{"year":"2009/10","female":21,"male":6},{"year":"2010/11","female":20,"male":5},{"year":"2011/12","female":28,"male":7},{"year":"2012/13","female":25,"male":5},{"year":"2013/14","female":22,"male":5},{"year":"2014/15","female":30,"male":7},{"year":"2015/16","female":31,"male":5}],"students":{"2001/02":[{"class_level":"Vorklassen","female":20,"male":14},{"class_level":"Jahrgangsstufe 01","female":22,"male":29},{"class_level":"Jahrgangsstufe 02","female":33,"male":30},{"class_level":"Jahrgangsstufe 03","female":23,"male":26},{"class_level":"Jahrgangsstufe 04","female":34,"male":37},{"class_level":"Jahrgangsstufe 05","female":32,"male":28},{"class_level":"Jahrgangsstufe 06","female":30,"male":43}],"2002/03":[{"class_level":"Vorklassen","female":14,"male":19},{"class_level":"Jahrgangsstufe 01","female":25,"male":19},{"class_level":"Jahrgangsstufe 02","female":20,"male":25},{"class_level":"Jahrgangsstufe 03","female":32,"male":30},{"class_level":"Jahrgangsstufe 04","female":26,"male":26},{"class_level":"Jahrgangsstufe 05","female":35,"male":32},{"class_level":"Jahrgangsstufe 06","female":32,"male":28}],"2003/04":[{"class_level":"Vorklassen","female":27,"male":25},{"class_level":"Jahrgangsstufe 01","female":30,"male":26},{"class_level":"Jahrgangsstufe 02","female":20,"male":16},{"class_level":"Jahrgangsstufe 03","female":21,"male":29},{"class_level":"Jahrgangsstufe 04","female":27,"male":29},{"class_level":"Jahrgangsstufe 05","female":22,"male":22},{"class_level":"Jahrgangsstufe 06","female":35,"male":33}],"2004/05":[{"class_level":"Vorklassen","female":29,"male":27},{"class_level":"Jahrgangsstufe 01","female":41,"male":30},{"class_level":"Jahrgangsstufe 02","female":33,"male":30},{"class_level":"Jahrgangsstufe 03","female":22,"male":19},{"class_level":"Jahrgangsstufe 04","female":18,"male":29},{"class_level":"Jahrgangsstufe 05","female":25,"male":24},{"class_level":"Jahrgangsstufe 06","female":22,"male":22}],"2005/06":[{"class_level":"Jahrgangsstufe 01","female":43,"male":38},{"class_level":"Jahrgangsstufe 02","female":41,"male":30},{"class_level":"Jahrgangsstufe 03","female":33,"male":35},{"class_level":"Jahrgangsstufe 04","female":20,"male":18},{"class_level":"Jahrgangsstufe 05","female":12,"male":26},{"class_level":"Jahrgangsstufe 06","female":24,"male":26}],"2006/07":[{"class_level":"Schulanfangsphase","female":79,"male":69},{"class_level":"Jahrgangsstufe 03","female":36,"male":33},{"class_level":"Jahrgangsstufe 04","female":33,"male":37},{"class_level":"Jahrgangsstufe 05","female":22,"male":18},{"class_level":"Jahrgangsstufe 06","female":9,"male":25}],"2007/08":[{"class_level":"Jahrgangsstufe 01","female":32,"male":28},{"class_level":"Jahrgangsstufe 02","female":35,"male":35},{"class_level":"Jahrgangsstufe 03","female":33,"male":34},{"class_level":"Jahrgangsstufe 04","female":34,"male":29},{"class_level":"Jahrgangsstufe 05","female":28,"male":25},{"class_level":"Jahrgangsstufe 06","female":22,"male":19}],"2008/09":[{"class_level":"Schulanfangsphase","female":49,"male":48},{"class_level":"Jahrgangsstufe 03","female":35,"male":36},{"class_level":"Jahrgangsstufe 04","female":33,"male":29},{"class_level":"Jahrgangsstufe 05","female":29,"male":28},{"class_level":"Jahrgangsstufe 06","female":28,"male":21}],"2009/10":[{"class_level":"Schulanfangsphase","female":58,"male":56},{"class_level":"Jahrgangsstufe 03","female":24,"male":31},{"class_level":"Jahrgangsstufe 04","female":25,"male":27},{"class_level":"Jahrgangsstufe 05","female":27,"male":29},{"class_level":"Jahrgangsstufe 06","female":29,"male":32}],"2010/11":[{"class_level":"Schulanfangsphase","female":63,"male":68},{"class_level":"Jahrgangsstufe 03","female":20,"male":20},{"class_level":"Jahrgangsstufe 04","female":23,"male":30},{"class_level":"Jahrgangsstufe 05","female":24,"male":20},{"class_level":"Jahrgangsstufe 06","female":27,"male":29}],"2011/12":[{"class_level":"Schulanfangsphase","female":67,"male":77},{"class_level":"Jahrgangsstufe 03","female":24,"male":15},{"class_level":"Jahrgangsstufe 04","female":21,"male":18},{"class_level":"Jahrgangsstufe 05","female":19,"male":26},{"class_level":"Jahrgangsstufe 06","female":32,"male":43}],"2012/13":[{"class_level":"Schulanfangsphase","female":73,"male":60},{"class_level":"Jahrgangsstufe 03","female":21,"male":31},{"class_level":"Jahrgangsstufe 04","female":22,"male":18},{"class_level":"Jahrgangsstufe 05","female":19,"male":19},{"class_level":"Jahrgangsstufe 06","female":22,"male":26}],"2013/14":[{"class_level":"Schulanfangsphase","female":71,"male":67},{"class_level":"Jahrgangsstufe 03","female":25,"male":31},{"class_level":"Jahrgangsstufe 04","female":21,"male":29},{"class_level":"Jahrgangsstufe 05","female":20,"male":16},{"class_level":"Jahrgangsstufe 06","female":25,"male":29}],"2014/15":[{"class_level":"Schulanfangsphase","female":64,"male":71},{"class_level":"Jahrgangsstufe 03","female":37,"male":25},{"class_level":"Jahrgangsstufe 04","female":21,"male":31},{"class_level":"Jahrgangsstufe 05","female":21,"male":28},{"class_level":"Jahrgangsstufe 06","female":32,"male":31}],"2015/16":[{"class_level":"Schulanfangsphase","female":64,"male":71},{"class_level":"Jahrgangsstufe 03","female":34,"male":36},{"class_level":"Jahrgangsstufe 04","female":37,"male":26},{"class_level":"Jahrgangsstufe 05","female":11,"male":29},{"class_level":"Jahrgangsstufe 06","female":28,"male":33}],"2016/17":[{"class_level":"Schulanfangsphase (Saph 1-2)","female":70,"male":67},{"class_level":"Jahrgangsstufe 03 (incl JüL 1-3)","female":40,"male":42},{"class_level":"Jahrgangsstufe 04","female":32,"male":30},{"class_level":"Jahrgangsstufe 05","female":30,"male":22},{"class_level":"Jahrgangsstufe 06 (incl JüL 4-6)","female":17,"male":35}]}},"programs":{"working_groups":[{"name":"Theater","category":"Kunst / Kultur","entity":"Theater"},{"name":"Radfahren","category":"Sport","entity":"Radfahren"},{"name":"Fußball","category":"Sport","entity":"Fußball"},{"name":"Tanz","category":"Musik / Tanz","entity":"Tanz"},{"name":"Schülerzeitung","category":"Literatur / Medien","entity":"Schülerzeitung"},{"name":"Keyboard","category":"Musik / Tanz","entity":"Keyboard"},{"name":"Streetball","category":"no category","entity":"no group"}],"programs":[]},"concept":"Leitbild unserer Nehring-Grundschule1 Wir in der Nehring-Grundschule sehen uns als individuelle Persönlichkeiten 2 Wir wissen um die unterschiedlichen Voraussetzungen der Kinder und fördern und fordern sie emotional. sozial,  intellektuell und interkulturell3 Wir pflegen an unserer Schule einen respektvollen Umgang miteinander und schätzen kulturelle und persönliche Unterschiede4 Wir schaffen eine Atmosphäre in der alle Kinder mit Neugierde und Freude lernen können5 Wir entwickeln durch den Wechsel vonoffenen, gebundenen und projektorientierten Arbeitsformen eine positive Arbeitshaltung, mit der Kinder selbstständig und selbstbestimmte Lernfortschritte erzielen6 Wir verstehen uns als eine große Gemeinschaft, zu deren Wohl alle am Schulleben Beteiligten engagiert und vertrauensvoll zusammenarbeiten","partner":[],"state":"BE","lon":13.2940489,"lat":52.5154294}
