{"name":"Sächsische Landeszentrale für politische Bildung","id":"SN-4030003-0","address":" Schützenhofstraße 36-38 01129 Dresden   ","school_type":"Weiterbildungsstätte Sächsische Landeszentrale für politische Bildung","legal_status":1,"fax":"0351/8531855 ","phone":"0351/8531810 ","website":"http://www.slpb.de","email":"Carola.Goerschel@slpb.smk.sachsen.de","provider":"Freistaat Sachsen - Staatsministerium für Kultus","director":"Herr Richter, Frank","full_time_school":false,"profile":{"students":{"2013":[],"2014":[],"2015":[]},"teacher":[]},"programs":{"programs":[]},"partner":[],"state":"SN","lon":13.7094933,"lat":51.0961153}
