{"name":"Albert-Schweitzer-Gymnasium","id":"SN-4540332-0","address":" Pleißaer Straße 10 09212 Limbach-Oberfrohna OT Limbach  ","school_type":"Gymnasium","legal_status":1,"fax":"03722/83044 ","phone":"03722/93220 ","website":"http://www.gymnasium-limbach.de","email":"sl.gym.limb.schweitzer@web.de","provider":"Stadt Limbach-Oberfrohna","director":"Herr Engel, Holger","full_time_school":false,"profile":{"students":{"2013":[{"class_level":5,"male":56,"female":55},{"class_level":6,"male":38,"female":45},{"class_level":7,"male":36,"female":60},{"class_level":8,"male":37,"female":49},{"class_level":9,"male":42,"female":47},{"class_level":10,"male":48,"female":51}],"2014":[{"class_level":5,"male":45,"female":51},{"class_level":6,"male":55,"female":54},{"class_level":7,"male":37,"female":47},{"class_level":8,"male":33,"female":58},{"class_level":9,"male":33,"female":46},{"class_level":10,"male":37,"female":45}],"2015":[{"class_level":5,"male":49,"female":48},{"class_level":6,"male":47,"female":50},{"class_level":7,"male":53,"female":56},{"class_level":8,"male":38,"female":42},{"class_level":9,"male":29,"female":53},{"class_level":10,"male":31,"female":48}]},"teacher":[{"year":"2016/2017","male":14,"female":40},{"year":"2015/2016","male":16,"female":40},{"year":"2014/2015","male":15,"female":42},{"year":"2013/2014","male":15,"female":39},{"year":"2012/2013","male":16,"female":40}]},"programs":{"programs":[],"working_groups":[{"name":null,"category":"no category","entity":"no group"},{"name":null,"category":"no category","entity":"no group"},{"name":null,"category":"no category","entity":"no group"},{"name":null,"category":"no category","entity":"no group"},{"name":null,"category":"no category","entity":"no group"}]},"partner":[{"name":"BA Glauchau","focus":"Keine Angabe","type":{"detail":"Ausbildungszentrum","grob":"ffentliche Infrastruktur"}},{"name":"FFw Limbach-Oberfrohna","focus":"Keine Angabe","type":{"detail":"Feuerwehr","grob":"ffentliche Infrastruktur"}},{"name":"Diakonie Stadtmission Chemnitz e.V.","focus":"Keine Angabe","type":{"detail":"kirchliche Einrichtung","grob":"Religise Einrichtung"}},{"name":"Tennisclub Limbach-Oberfrohna","focus":"Keine Angabe","type":{"detail":"Sportverein","grob":"Gemeinntziger Akteur"}},{"name":"Reitsportverein Rhrsdorf und Reitsportverein Limbach-Oberfrohna","focus":"Keine Angabe","type":{"detail":"Sportverein","grob":"Gemeinntziger Akteur"}},{"name":"TU Chemnitz","focus":"Keine Angabe","type":{"detail":"Universitt","grob":"ffentliche Infrastruktur"}},{"name":"DRK Limbach-Oberfrohna","focus":"Keine Angabe","type":{"detail":"Verein","grob":"Gemeinntziger Akteur"}},{"name":"VELA e.V.","focus":"Organisation von Veranstaltungen zur StudienberationTage der Wissenschaft unter Einbeziehung von SchlervortrgenUntersttzung von Schulprojekten , z.B. Kinderchor","type":{"detail":"Verein","grob":"Gemeinntziger Akteur"}},{"name":"Sparkasse Chemnitz","focus":"Keine Angabe","type":{"detail":"Wirtschaft","grob":"Wirtschaftsakteur"}},{"name":"Volksbank Chemnitz /Limbach-Oberfrohna","focus":"Keine Angabe","type":{"detail":"Wirtschaft","grob":"Wirtschaftsakteur"}},{"name":"Starrag Heckert Chemnitz","focus":"Keine Angabe","type":{"detail":"Wirtschaft","grob":"Wirtschaftsakteur"}},{"name":"Wirtschaftspartner \\\\\\Boehringer Ingelheim\\\\\\ und \\\\\\Schott-Glaswerke\\\\\\","focus":"Keine Angabe","type":{"detail":"Wirtschaft","grob":"Wirtschaftsakteur"}}],"concept":" ","state":"SN","lon":12.773238,"lat":50.854618}
