{"name":"Grundschule Leubnitz","id":"SN-4511234-0","address":" Schulstraße 3 08412 Werdau OT Leubnitz  ","school_type":"Grundschule","legal_status":1,"fax":"03761/186344 ","phone":"03761/86966 ","website":"http://www.grundschule-leubnitz.de","email":"grundschule-leubnitz@t-online.de","provider":"Stadt Werdau","director":"Frau Franke, Ulrike","full_time_school":false,"profile":{"students":{"2013":[{"class_level":1,"male":24,"female":25},{"class_level":2,"male":17,"female":27},{"class_level":3,"male":14,"female":27},{"class_level":4,"male":27,"female":26}],"2014":[{"class_level":1,"male":28,"female":22},{"class_level":2,"male":21,"female":27},{"class_level":3,"male":15,"female":23},{"class_level":4,"male":14,"female":27}],"2015":[{"class_level":1,"male":21,"female":25},{"class_level":2,"male":26,"female":20},{"class_level":3,"male":21,"female":26},{"class_level":4,"male":17,"female":22}]},"teacher":[{"year":"2016/2017","male":0,"female":11},{"year":"2015/2016","male":1,"female":10},{"year":"2014/2015","male":0,"female":9},{"year":"2013/2014","male":0,"female":10},{"year":"2012/2013","male":1,"female":13}]},"programs":{"programs":[],"working_groups":[{"name":"Offenes Spielangebot","category":"Berufsorientierung","entity":"Offenes Spielangebot"},{"name":"Schülerbibliothek","category":"Literatur / Medien","entity":"Schülerbibliothek"},{"name":"Fitnessclub","category":"Sport","entity":"Fitnessclub"},{"name":"Fußball","category":"Sport","entity":"Fußball"},{"name":"Leichtathletik","category":"Sport","entity":"Leichtathletik"},{"name":"Maschineschreiben","category":"Naturwissenschaft / Technik","entity":"Maschineschreiben"},{"name":"Chor","category":"Musik / Tanz","entity":"Chor"},{"name":"Keramik/ Töpfern","category":"no category","entity":"no group"},{"name":"Darstellendes Spiel/Theater","category":"Kultur / Kunst","entity":"Darstellendes Spiel/Theater"},{"name":"künstlerisches Gestalten","category":"Kultur / Kunst","entity":"künstlerisches Gestalten"},{"name":"Tanz","category":"Musik / Tanz","entity":"Tanz"},{"name":"Musiktheater","category":"Kultur / Kunst","entity":"Musiktheater"},{"name":"Schülerzeitung","category":"Literatur / Medien","entity":"Schülerzeitung"},{"name":"Computer/ Informatik/ Internet","category":"no category","entity":"no group"},{"name":"Konzentrationstraining","category":"Sport","entity":"Konzentrationstraining"},{"name":"1. Hilfe/Sanitäter","category":"Gesellschaft / Partizipation","entity":"1. Hilfe/Sanitäter"},{"name":"Hausaufgabenbetreuung","category":"Berufsorientierung","entity":"Hausaufgabenbetreuung"}]},"partner":[{"name":"HC Fraureuth, Abteilung Handball","focus":"Keine Angabe","type":{"detail":"Sportverein","grob":"Gemeinntziger Akteur"}},{"name":"alle Kitas der Stadt Werdau","focus":"Umsetzen der Bildungsstandards um die Kinder auf die Schule vor zu bereitenSchuleingangsphase zu optimieren","type":{"detail":"Kindertagessttte","grob":"ffentliche Infrastruktur"}},{"name":"Oberschule Leubnitz","focus":"Vorbereitung der Grundschler auf weiterfhrende Schulen","type":{"detail":"Partnerschule","grob":"Partnerschule"}},{"name":"SV Rot-Wei Werdau e.V. Abteilung Fuball","focus":"Keine Angabe","type":{"detail":"Verein","grob":"Gemeinntziger Akteur"}},{"name":"Schulfrderverein Leubnitz","focus":"Beschaffung materieller MittelAusgestaltung SchulfeiernVorbereitung RanzenpartyVorbereitung der Schulanfnger auf die GS","type":{"detail":"Verein","grob":"Gemeinntziger Akteur"}}],"concept":"Unsere Schule - ein Ort zum Wohlfühlen ","state":"SN","lon":12.364941,"lat":50.721628}
